Workbook

Sheet Resumen
A1: CanSat Universitario 2026–2027 | Control de masa, energía y presupuesto
A4: Parámetros de diseño | D4: Batería seleccionada
A5: Masa objetivo [g] | B5: 500 | D5: Modelo | E5: {=IF(COUNTIF(Baterias!$A$2:$A$11,"Sí")=1,INDEX(Baterias!$B$2:$B$11,MATCH("Sí",Baterias!$A$2:$A$11,0)),"Revisar selección")} -> 18650
A6: Tolerancia de masa [g] | B6: 10 | D6: Tensión pack [V] | E6: =SUMIF(Baterias!$A$2:$A$11,"Sí",Baterias!$H$2:$H$11) -> 3.7
A7: Presupuesto máximo CanSat [ARS] | B7: 1000000 | D7: Capacidad pack [mAh] | E7: =SUMIF(Baterias!$A$2:$A$11,"Sí",Baterias!$I$2:$I$11) -> 6000
A8: Autonomía mínima [h] | B8: 2 | D8: Energía utilizable [Wh] | E8: =SUMIF(Baterias!$A$2:$A$11,"Sí",Baterias!$L$2:$L$11) -> 19.98
A9: Margen energético de diseño [%] | B9: 0.2 | D9: Masa pack [g] | E9: =SUMIF(Baterias!$A$2:$A$11,"Sí",Baterias!$O$2:$O$11) -> 93.2
A10: Eficiencia global de regulación [%] | B10: 0.85 | D10: Costo pack [ARS] | E10: =SUMIF(Baterias!$A$2:$A$11,"Sí",Baterias!$R$2:$R$11) -> 0
D11: N.º candidatas seleccionadas | E11: =COUNTIF(Baterias!$A$2:$A$11,"Sí") -> 1
A12: Indicadores principales
A13: Masa total CanSat + batería [g] | B13: =SUMIFS(Componentes!$P$2:$P$151,Componentes!$C$2:$C$151,"Sí")+SUMIF(Baterias!$A$2:$A$11,"Sí",Baterias!$O$2:$O$11) -> 189.7114 | D13: Cómo usar la planilla
A14: Estado masa | B14: =IF(AND(B13>=B5-B6,B13<=B5+B6),"CUMPLE","REVISAR") -> REVISAR | D14: 1. Cargar cada sensor, módulo, pieza mecánica y elemento de estación terrena en «Componentes».
A15: Costo CanSat + batería [ARS] | B15: =SUMIFS(Componentes!$R$2:$R$151,Componentes!$C$2:$C$151,"Sí")+SUMIF(Baterias!$A$2:$A$11,"Sí",Baterias!$R$2:$R$11) -> 0 | D15: 2. Completar tensión, corrientes y duty activo para estimar potencia media.
A16: Presupuesto restante [ARS] | B16: =B7-B15 -> 1000000 | D16: 3. Cargar candidatos de batería en «Baterias» y marcar solo uno como «Sí».
A17: Potencia media a bordo [W] | B17: =SUMIFS(Componentes!$N$2:$N$151,Componentes!$C$2:$C$151,"Sí") -> 4.0689267 | D17: 4. La masa y costo del CanSat incluyen solo filas marcadas «Computa en CanSat? = Sí» más la batería seleccionada.
A18: Energía requerida con margen [Wh] | B18: =B17*B8/B10*(1+B9) -> 11.488734 | D18: 5. Los parámetros editables del cuadro superior pueden modificarse si CONAE actualiza requisitos o si se adopta otro margen de diseño.
A19: Autonomía batería seleccionada [h] | B19: =SUMIF(Baterias!$A$2:$A$11,"Sí",Baterias!$S$2:$S$11) -> 1.4782307
A20: Estado autonomía | B20: =IF(B19="","SIN BATERÍA",IF(B19>=B8,"CUMPLE","NO CUMPLE")) -> NO CUMPLE
A21: Masa disponible hasta 510 g [g] | B21: =(B5+B6)-B13 -> 320.2886
A24: Subsistema | B24: Masa [g] | C24: Costo [ARS] | D24: Potencia [W]
A25: Adquisición de datos | B25: =SUMIFS(Componentes!$P$2:$P$151,Componentes!$B$2:$B$151,A25,Componentes!$C$2:$C$151,"Sí") -> 22 | C25: =SUMIFS(Componentes!$R$2:$R$151,Componentes!$B$2:$B$151,A25,Componentes!$C$2:$C$151,"Sí") -> 0 | D25: =SUMIFS(Componentes!$N$2:$N$151,Componentes!$B$2:$B$151,A25,Componentes!$C$2:$C$151,"Sí") -> 0.022710239
A26: Control / Software | B26: =SUMIFS(Componentes!$P$2:$P$151,Componentes!$B$2:$B$151,A26,Componentes!$C$2:$C$151,"Sí") -> 36.8114 | C26: =SUMIFS(Componentes!$R$2:$R$151,Componentes!$B$2:$B$151,A26,Componentes!$C$2:$C$151,"Sí") -> 0 | D26: =SUMIFS(Componentes!$N$2:$N$151,Componentes!$B$2:$B$151,A26,Componentes!$C$2:$C$151,"Sí") -> 3.1753851
A27: Comunicación | B27: =SUMIFS(Componentes!$P$2:$P$151,Componentes!$B$2:$B$151,A27,Componentes!$C$2:$C$151,"Sí") -> 8 | C27: =SUMIFS(Componentes!$R$2:$R$151,Componentes!$B$2:$B$151,A27,Componentes!$C$2:$C$151,"Sí") -> 0 | D27: =SUMIFS(Componentes!$N$2:$N$151,Componentes!$B$2:$B$151,A27,Componentes!$C$2:$C$151,"Sí") -> 0.6385533
A28: Navegación | B28: =SUMIFS(Componentes!$P$2:$P$151,Componentes!$B$2:$B$151,A28,Componentes!$C$2:$C$151,"Sí") -> 8 | C28: =SUMIFS(Componentes!$R$2:$R$151,Componentes!$B$2:$B$151,A28,Componentes!$C$2:$C$151,"Sí") -> 0 | D28: =SUMIFS(Componentes!$N$2:$N$151,Componentes!$B$2:$B$151,A28,Componentes!$C$2:$C$151,"Sí") -> 0.081618
A29: Registro / Video | B29: =SUMIFS(Componentes!$P$2:$P$151,Componentes!$B$2:$B$151,A29,Componentes!$C$2:$C$151,"Sí") -> 19 | C29: =SUMIFS(Componentes!$R$2:$R$151,Componentes!$B$2:$B$151,A29,Componentes!$C$2:$C$151,"Sí") -> 0 | D29: =SUMIFS(Componentes!$N$2:$N$151,Componentes!$B$2:$B$151,A29,Componentes!$C$2:$C$151,"Sí") -> 0
A30: Almacenamiento | B30: =SUMIFS(Componentes!$P$2:$P$151,Componentes!$B$2:$B$151,A30,Componentes!$C$2:$C$151,"Sí") -> 2.7 | C30: =SUMIFS(Componentes!$R$2:$R$151,Componentes!$B$2:$B$151,A30,Componentes!$C$2:$C$151,"Sí") -> 0 | D30: =SUMIFS(Componentes!$N$2:$N$151,Componentes!$B$2:$B$151,A30,Componentes!$C$2:$C$151,"Sí") -> 0.00066
A31: Mecánico / Estructural | B31: =SUMIFS(Componentes!$P$2:$P$151,Componentes!$B$2:$B$151,A31,Componentes!$C$2:$C$151,"Sí") -> 0 | C31: =SUMIFS(Componentes!$R$2:$R$151,Componentes!$B$2:$B$151,A31,Componentes!$C$2:$C$151,"Sí") -> 0 | D31: =SUMIFS(Componentes!$N$2:$N$151,Componentes!$B$2:$B$151,A31,Componentes!$C$2:$C$151,"Sí") -> 0
A32: Descenso / Recuperación | B32: =SUMIFS(Componentes!$P$2:$P$151,Componentes!$B$2:$B$151,A32,Componentes!$C$2:$C$151,"Sí") -> 0 | C32: =SUMIFS(Componentes!$R$2:$R$151,Componentes!$B$2:$B$151,A32,Componentes!$C$2:$C$151,"Sí") -> 0 | D32: =SUMIFS(Componentes!$N$2:$N$151,Componentes!$B$2:$B$151,A32,Componentes!$C$2:$C$151,"Sí") -> 0.15
A33: Misión secundaria | B33: =SUMIFS(Componentes!$P$2:$P$151,Componentes!$B$2:$B$151,A33,Componentes!$C$2:$C$151,"Sí") -> 0 | C33: =SUMIFS(Componentes!$R$2:$R$151,Componentes!$B$2:$B$151,A33,Componentes!$C$2:$C$151,"Sí") -> 0 | D33: =SUMIFS(Componentes!$N$2:$N$151,Componentes!$B$2:$B$151,A33,Componentes!$C$2:$C$151,"Sí") -> 0
A34: Otros | B34: =SUMIFS(Componentes!$P$2:$P$151,Componentes!$B$2:$B$151,A34,Componentes!$C$2:$C$151,"Sí") -> 0 | C34: =SUMIFS(Componentes!$R$2:$R$151,Componentes!$B$2:$B$151,A34,Componentes!$C$2:$C$151,"Sí") -> 0 | D34: =SUMIFS(Componentes!$N$2:$N$151,Componentes!$B$2:$B$151,A34,Componentes!$C$2:$C$151,"Sí") -> 0
A35: Batería seleccionada | B35: =SUMIF(Baterias!$A$2:$A$11,"Sí",Baterias!$O$2:$O$11) -> 93.2 | C35: =SUMIF(Baterias!$A$2:$A$11,"Sí",Baterias!$R$2:$R$11) -> 0 | D35: 0
A38: Costos fuera del límite C9
A39: Costo estación terrena / soporte [ARS] | B39: =SUMIFS(Componentes!$R$2:$R$151,Componentes!$C$2:$C$151,"No") -> 0
A40: Costo total del proyecto [ARS] | B40: =B15+B39 -> 0

Sheet Componentes
A1: ID | B1: Subsistema | C1: Computa en CanSat? | D1: Aplicación | E1: Tipo | F1: Componente / Modelo | G1: Función | H1: Cantidad | I1: Tensión [V] | J1: Corriente activa [mA] | K1: Corriente reposo [mA] | L1: Duty activo [%] | M1: Corriente media [mA] | N1: Potencia media [W] | O1: Masa unitaria [g] | P1: Masa total [g] | Q1: Precio unitario [ARS] | R1: Costo total [ARS] | S1: Interfaz | T1: Protocolo / Frecuencia | U1: Estado | V1: Fuente / Link | W1: Notas
A2: C-001 | B2: Control / Software | C2: Sí | D2: Común | E2: Microcontrolador | F2: STM32 | G2: Unidad principal de control | H2: 1 | I2: 3.3 | J2: =36 -> 36 | K2: =5.5 -> 5.5 | L2: =1 -> 1 | M2: =IF(OR(F2="",L2=""),"",H2*(J2*L2+K2*(1-L2))) -> 36 | N2: =IF(M2="","",I2*M2/1000) -> 0.1188 | O2: 8 | P2: =IF(F2="","",H2*O2) -> 8 | R2: =IF(F2="","",H2*Q2) -> 0 | U2: Descartado
A3: C-002 | B3: Control / Software | C3: Sí | D3: Común | E3: Microcontrolador | F3: ESP32-S3 | G3: Unidad principal de control | H3: =1 -> 1 | I3: =3.3 -> 3.3 | J3: =47.3 -> 47.3 | K3: =36.1 -> 36.1 | L3: =1 -> 1 | M3: =IF(OR(F3="",L3=""),"",H3*(J3*L3+K3*(1-L3))) -> 47.3 | N3: =IF(M3="","",I3*M3/1000) -> 0.15609 | O3: =15 -> 15 | P3: =IF(F3="","",H3*O3) -> 15 | R3: =IF(F3="","",H3*Q3) -> 0 | U3: Seleccionado | V3: https://naylampmechatronics.com/espressif-esp/1206-esp32-s3-devkitc-1-44-pin-esp32-s3-wifi-usb-c.html
A4: C-003 | B4: Adquisición de datos | C4: Sí | D4: Misión principal | E4: Sensor | F4: BMP280 | G4: Presión / temperatura / altitud barométrica | H4: 1 | I4: =3.3 -> 3.3 | J4: =0.72 -> 0.72 | K4: =0.0001 -> 0.0001 | L4: =0.00375 -> 0.00375 | M4: =IF(OR(F4="",L4=""),"",H4*(J4*L4+K4*(1-L4))) -> 0.002799625 | N4: =IF(M4="","",I4*M4/1000) -> 9.2387625e-06 | O4: 2 | P4: =IF(F4="","",H4*O4) -> 2 | R4: =IF(F4="","",H4*Q4) -> 0 | S4: I2C / SPI | U4: Seleccionado
A5: C-004 | B5: Adquisición de datos | C5: Sí | D5: Misión principal | E5: IMU | F5: GY-521 | G5: Aceleración y velocidad angular | H5: 1 | I5: =5 -> 5 | J5: =3.9 -> 3.9 | K5: =0.005 -> 0.005 | L5: =1 -> 1 | M5: =IF(OR(F5="",L5=""),"",H5*(J5*L5+K5*(1-L5))) -> 3.9 | N5: =IF(M5="","",I5*M5/1000) -> 0.0195 | O5: =2.1 -> 2.1 | P5: =IF(F5="","",H5*O5) -> 2.1 | R5: =IF(F5="","",H5*Q5) -> 0 | S5: I2C / SPI | U5: Seleccionado
A6: C-005 | B6: Navegación | C6: Sí | D6: Misión principal | E6: GPS | F6: NEO-M8N | G6: Posición, altitud y tiempo GPS | H6: 1 | I6: =3 -> 3 | J6: =34 -> 34 | K6: =0.03 -> 0.03 | L6: =0.8 -> 0.8 | M6: =IF(OR(F6="",L6=""),"",H6*(J6*L6+K6*(1-L6))) -> 27.206 | N6: =IF(M6="","",I6*M6/1000) -> 0.081618 | O6: =8 -> 8 | P6: =IF(F6="","",H6*O6) -> 8 | R6: =IF(F6="","",H6*Q6) -> 0 | S6: UART | U6: Seleccionado
A7: C-006 | B7: Comunicación | C7: Sí | D7: Común | E7: Radio | F7: XBee-Pro 900HP | G7: Telemetría y telecomandos | H7: 1 | I7: =3.3 -> 3.3 | J7: =215 -> 215 | K7: =0.01 -> 0.01 | L7: =0.9 -> 0.9 | M7: =IF(OR(F7="",L7=""),"",H7*(J7*L7+K7*(1-L7))) -> 193.501 | N7: =IF(M7="","",I7*M7/1000) -> 0.6385533 | O7: =8 -> 8 | P7: =IF(F7="","",H7*O7) -> 8 | R7: =IF(F7="","",H7*Q7) -> 0 | S7: SPI / UART | T7: 915–928 MHz o 2.4 GHz | U7: Seleccionado
A8: C-007 | B8: Registro / Video | C8: Sí | D8: Misión principal | E8: Cámara | F8: Xiao ESP32SE Sense - OV2640 | G8: Registro de video hacia cenit / nadir | H8: =2 -> 2 | I8: =5 -> 5 | J8: =140 -> 140 | K8: =38.3 -> 38.3 | M8: =IF(OR(F8="",L8=""),"",H8*(J8*L8+K8*(1-L8))) | N8: =IF(M8="","",I8*M8/1000) | O8: =8 -> 8 | P8: =IF(F8="","",H8*O8) -> 16 | R8: =IF(F8="","",H8*Q8) -> 0 | U8: Seleccionado
A9: C-008 | B9: Almacenamiento | C9: Sí | D9: Común | E9: Memoria | F9: MicroSD 8GB | G9: Respaldo de telemetría / datos | H9: =3 -> 3 | I9: =3.3 -> 3.3 | M9: =IF(OR(F9="",L9=""),"",H9*(J9*L9+K9*(1-L9))) | N9: =IF(M9="","",I9*M9/1000) | O9: =0.5 -> 0.5 | P9: =IF(F9="","",H9*O9) -> 1.5 | R9: =IF(F9="","",H9*Q9) -> 0 | S9: SPI | U9: Seleccionado
A10: C-009 | B10: Descenso / Recuperación | C10: Sí | D10: Misión principal | E10: Mecanismo | G10: Liberación del segundo sistema de descenso | H10: 1 | M10: =IF(OR(F10="",L10=""),"",H10*(J10*L10+K10*(1-L10))) | N10: =IF(M10="","",I10*M10/1000) | P10: =IF(F10="","",H10*O10) | R10: =IF(F10="","",H10*Q10) | U10: Por definir
A11: C-010 | B11: Descenso / Recuperación | C11: Sí | D11: Misión principal | E11: Baliza | F11: Diyables X5 | G11: Baliza audible independiente | H11: 1 | I11: =5 -> 5 | J11: 30 | K11: 0.001 | L11: =1 -> 1 | M11: =IF(OR(F11="",L11=""),"",H11*(J11*L11+K11*(1-L11))) -> 30 | N11: =IF(M11="","",I11*M11/1000) -> 0.15 | P11: =IF(F11="","",H11*O11) -> 0 | R11: =IF(F11="","",H11*Q11) -> 0 | U11: Seleccionado
A12: C-011 | B12: Mecánico / Estructural | C12: Sí | D12: Común | E12: Estructura | G12: Estructura / contenedor del CanSat | H12: 1 | M12: =IF(OR(F12="",L12=""),"",H12*(J12*L12+K12*(1-L12))) | N12: =IF(M12="","",I12*M12/1000) | P12: =IF(F12="","",H12*O12) | R12: =IF(F12="","",H12*Q12) | U12: Por definir
A13: C-012 | B13: Mecánico / Estructural | C13: Sí | D13: Común | E13: Cableado / conectores | G13: Cableado, conectores y fijaciones | H13: 1 | M13: =IF(OR(F13="",L13=""),"",H13*(J13*L13+K13*(1-L13))) | N13: =IF(M13="","",I13*M13/1000) | P13: =IF(F13="","",H13*O13) | R13: =IF(F13="","",H13*Q13) | U13: Por definir
A14: C-013 | B14: Adquisición de datos | C14: Sí | D14: Misión principal | E14: Sensor solar | F14: Panel Solar Epóxico | G14: Detección de radiación solar exigida por CONAE | H14: 1 | M14: =IF(OR(F14="",L14=""),"",H14*(J14*L14+K14*(1-L14))) | N14: =IF(M14="","",I14*M14/1000) | O14: 14 | P14: =IF(F14="","",H14*O14) -> 14 | R14: =IF(F14="","",H14*Q14) -> 0 | U14: Candidato | V14: https://www.sdgreensun.com/products_detail.php?cid=88&id=228&utm_source=chatgpt.com
A15: C-014 | B15: Misión secundaria | C15: Sí | D15: Misión secundaria | E15: Sensor / módulo | G15: Hardware específico de la misión secundaria | H15: 1 | M15: =IF(OR(F15="",L15=""),"",H15*(J15*L15+K15*(1-L15))) | N15: =IF(M15="","",I15*M15/1000) | P15: =IF(F15="","",H15*O15) | R15: =IF(F15="","",H15*Q15) | U15: Por definir
A16: G-001 | B16: Estación terrena | C16: No | D16: Común | E16: Radio | G16: Radio de estación terrena | H16: 1 | M16: =IF(OR(F16="",L16=""),"",H16*(J16*L16+K16*(1-L16))) | N16: =IF(M16="","",I16*M16/1000) | P16: =IF(F16="","",H16*O16) | R16: =IF(F16="","",H16*Q16) | U16: Por definir
A17: G-002 | B17: Estación terrena | C17: No | D17: Común | E17: Antena | G17: Antena de estación terrena | H17: 1 | M17: =IF(OR(F17="",L17=""),"",H17*(J17*L17+K17*(1-L17))) | N17: =IF(M17="","",I17*M17/1000) | P17: =IF(F17="","",H17*O17) | R17: =IF(F17="","",H17*Q17) | U17: Por definir
A18: G-003 | B18: Estación terrena | C18: No | D18: Común | E18: Computadora | G18: Computadora portátil / GCS | H18: 1 | M18: =IF(OR(F18="",L18=""),"",H18*(J18*L18+K18*(1-L18))) | N18: =IF(M18="","",I18*M18/1000) | P18: =IF(F18="","",H18*O18) | R18: =IF(F18="","",H18*Q18) | U18: Por definir
A19: C-015 | B19: Adquisición de datos | C19: Sí | D19: Misión principal | E19: Sensor | F19: INA219 | G19: Medición de Batería | H19: =1 -> 1 | I19: =3.3 -> 3.3 | J19: =0.7 -> 0.7 | K19: =0.006 -> 0.006 | L19: =1 -> 1 | M19: =IF(OR(F19="",L19=""),"",H19*(J19*L19+K19*(1-L19))) -> 0.7 | N19: =IF(M19="","",I19*M19/1000) -> 0.00231 | O19: =2 -> 2 | P19: =IF(F19="","",H19*O19) -> 2 | R19: =IF(F19="","",H19*Q19) -> 0 | U19: Seleccionado
A20: C-016 | B20: Almacenamiento | C20: Sí | D20: Común | E20: Memoria | F20: FRAM I2C | G20: Memoria no Volatil | H20: =1 -> 1 | I20: =3.3 -> 3.3 | J20: =0.2 -> 0.2 | K20: =0.027 -> 0.027 | L20: =1 -> 1 | M20: =IF(OR(F20="",L20=""),"",H20*(J20*L20+K20*(1-L20))) -> 0.2 | N20: =IF(M20="","",I20*M20/1000) -> 0.00066 | O20: =1.2 -> 1.2 | P20: =IF(F20="","",H20*O20) -> 1.2 | R20: =IF(F20="","",H20*Q20) -> 0 | U20: Seleccionado
A21: C-017 | B21: Adquisición de datos | C21: Sí | D21: Misión secundaria | E21: Sesnsor | F21: LIS3MDL | G21: Determinación de Orientación (Magnetómetro) | H21: =1 -> 1 | I21: =3.3 -> 3.3 | J21: =0.27 -> 0.27 | K21: =0.001 -> 0.001 | L21: =1 -> 1 | M21: =IF(OR(F21="",L21=""),"",H21*(J21*L21+K21*(1-L21))) -> 0.27 | N21: =IF(M21="","",I21*M21/1000) -> 0.000891 | O21: =1.5 -> 1.5 | P21: =IF(F21="","",H21*O21) -> 1.5 | R21: =IF(F21="","",H21*Q21) -> 0 | U21: Seleccionado
A22: C-018 | B22: Adquisición de datos | C22: Sí | D22: Misión secundaria | E22: Sensor | F22: BPW34 (Fotodiodo) | G22: Intensidad de Luz Solar | H22: =4 -> 4 | I22: =0 -> 0 | J22: =0 -> 0 | K22: =0 -> 0 | L22: =0 -> 0 | M22: =IF(OR(F22="",L22=""),"",H22*(J22*L22+K22*(1-L22))) -> 0 | N22: =IF(M22="","",I22*M22/1000) -> 0 | O22: =0.1 -> 0.1 | P22: =IF(F22="","",H22*O22) -> 0.4 | R22: =IF(F22="","",H22*Q22) -> 0 | U22: Seleccionado
A23: C-019 | B23: Control / Software | C23: Sí | D23: Común | E23: Conversor AD | F23: ADS1115 | G23: Convertir señal de diodos | H23: =1 -> 1 | I23: =3.3 -> 3.3 | J23: =0.15 -> 0.15 | K23: =0.0005 -> 0.0005 | L23: =1 -> 1 | M23: =IF(OR(F23="",L23=""),"",H23*(J23*L23+K23*(1-L23))) -> 0.15 | N23: =IF(M23="","",I23*M23/1000) -> 0.000495 | O23: =1.8 -> 1.8 | P23: =IF(F23="","",H23*O23) -> 1.8 | R23: =IF(F23="","",H23*Q23) -> 0 | U23: Seleccionado
A24: C-020 | B24: Registro / Video | C24: Sí | D24: Misión secundaria | E24: Cámara Infrarroja | F24: IMX219 NoIR | G24: Registro de video hacia nadir | H24: =1 -> 1 | M24: =IF(OR(F24="",L24=""),"",H24*(J24*L24+K24*(1-L24))) | N24: =IF(M24="","",I24*M24/1000) | O24: =3 -> 3 | P24: =IF(F24="","",H24*O24) -> 3 | R24: =IF(F24="","",H24*Q24) -> 0 | U24: Seleccionado | V24: https://www.raspberrypi.com/documentation/accessories/camera.html
A25: C-021 | B25: Control / Software | C25: Sí | D25: Misión secundaria | E25: Microprocesador | F25: Raspberry Pi Zero 2W | G25: Procesamiento de videos y datos | H25: =1 -> 1 | I25: =5 -> 5 | J25: =580 -> 580 | K25: =280 -> 280 | L25: =1 -> 1 | M25: =IF(OR(F25="",L25=""),"",H25*(J25*L25+K25*(1-L25))) -> 580 | N25: =IF(M25="","",I25*M25/1000) -> 2.9 | O25: =12 -> 12 | P25: =IF(F25="","",H25*O25) -> 12 | R25: =IF(F25="","",H25*Q25) -> 0 | U25: Seleccionado
A26: C-022 | B26: Control / Software | C26: Sí | D26: Común | E26: Reloj | F26: RV 3028 C7 | G26: Respaldo de hora para microcontrolador | H26: =1 -> 1 | I26: =3 -> 3 | J26: =0.000045 -> 4.5e-05 | K26: =0.000045 -> 4.5e-05 | L26: =1 -> 1 | M26: =IF(OR(F26="",L26=""),"",H26*(J26*L26+K26*(1-L26))) -> 4.5e-05 | N26: =IF(M26="","",I26*M26/1000) -> 1.35e-07 | O26: =0.0114 -> 0.0114 | P26: =IF(F26="","",H26*O26) -> 0.0114 | R26: =IF(F26="","",H26*Q26) -> 0 | U26: Seleccionado
M27: =IF(OR(F27="",L27=""),"",H27*(J27*L27+K27*(1-L27))) | N27: =IF(M27="","",I27*M27/1000) | P27: =IF(F27="","",H27*O27) | R27: =IF(F27="","",H27*Q27)
M28: =IF(OR(F28="",L28=""),"",H28*(J28*L28+K28*(1-L28))) | N28: =IF(M28="","",I28*M28/1000) | P28: =IF(F28="","",H28*O28) | R28: =IF(F28="","",H28*Q28)
M29: =IF(OR(F29="",L29=""),"",H29*(J29*L29+K29*(1-L29))) | N29: =IF(M29="","",I29*M29/1000) | P29: =IF(F29="","",H29*O29) | R29: =IF(F29="","",H29*Q29)
M30: =IF(OR(F30="",L30=""),"",H30*(J30*L30+K30*(1-L30))) | N30: =IF(M30="","",I30*M30/1000) | P30: =IF(F30="","",H30*O30) | R30: =IF(F30="","",H30*Q30)
M31: =IF(OR(F31="",L31=""),"",H31*(J31*L31+K31*(1-L31))) | N31: =IF(M31="","",I31*M31/1000) | P31: =IF(F31="","",H31*O31) | R31: =IF(F31="","",H31*Q31)
M32: =IF(OR(F32="",L32=""),"",H32*(J32*L32+K32*(1-L32))) | N32: =IF(M32="","",I32*M32/1000) | P32: =IF(F32="","",H32*O32) | R32: =IF(F32="","",H32*Q32)
M33: =IF(OR(F33="",L33=""),"",H33*(J33*L33+K33*(1-L33))) | N33: =IF(M33="","",I33*M33/1000) | P33: =IF(F33="","",H33*O33) | R33: =IF(F33="","",H33*Q33)
M34: =IF(OR(F34="",L34=""),"",H34*(J34*L34+K34*(1-L34))) | N34: =IF(M34="","",I34*M34/1000) | P34: =IF(F34="","",H34*O34) | R34: =IF(F34="","",H34*Q34)
M35: =IF(OR(F35="",L35=""),"",H35*(J35*L35+K35*(1-L35))) | N35: =IF(M35="","",I35*M35/1000) | P35: =IF(F35="","",H35*O35) | R35: =IF(F35="","",H35*Q35)
M36: =IF(OR(F36="",L36=""),"",H36*(J36*L36+K36*(1-L36))) | N36: =IF(M36="","",I36*M36/1000) | P36: =IF(F36="","",H36*O36) | R36: =IF(F36="","",H36*Q36)
M37: =IF(OR(F37="",L37=""),"",H37*(J37*L37+K37*(1-L37))) | N37: =IF(M37="","",I37*M37/1000) | P37: =IF(F37="","",H37*O37) | R37: =IF(F37="","",H37*Q37)
M38: =IF(OR(F38="",L38=""),"",H38*(J38*L38+K38*(1-L38))) | N38: =IF(M38="","",I38*M38/1000) | P38: =IF(F38="","",H38*O38) | R38: =IF(F38="","",H38*Q38)
... M151: =IF(OR(F151="",L151=""),"",H151*(J151*L151+K151*(1-L151))) | N151: =IF(M151="","",I151*M151/1000) | P151: =IF(F151="","",H151*O151) | R151: =IF(F151="","",H151*Q151)

Sheet Baterias
A1: Seleccionada | B1: Modelo | C1: Química | D1: Tensión celda [V] | E1: Capacidad celda [mAh] | F1: Serie (S) | G1: Paralelo (P) | H1: Tensión pack [V] | I1: Capacidad pack [mAh] | J1: Energía nominal [Wh] | K1: Fracción utilizable [%] | L1: Energía utilizable [Wh] | M1: Masa celda [g] | N1: Masa extra pack [g] | O1: Masa total pack [g] | P1: Precio celda [ARS] | Q1: Costo extra pack [ARS] | R1: Costo total pack [ARS] | S1: Autonomía estimada [h] | T1: Margen sobre mínimo [h] | U1: Estado autonomía | V1: Observaciones
A2: Sí | B2: 18650 | C2: Li-ion 18650 | D2: =3.7 -> 3.7 | E2: =3000 -> 3000 | F2: 1 | G2: =2 -> 2 | H2: =IF(OR(D2="",F2=""),"",D2*F2) -> 3.7 | I2: =IF(OR(E2="",G2=""),"",E2*G2) -> 6000 | J2: =IF(OR(H2="",I2=""),"",H2*I2/1000) -> 22.2 | K2: 0.9 | L2: =IF(J2="","",J2*K2) -> 19.98 | M2: =46.6 -> 46.6 | O2: =IF(M2="","",M2*F2*G2+N2) -> 93.2 | R2: =IF(P2="","",P2*F2*G2+Q2) | S2: =IF(OR(L2="",Resumen!$B$18=0),"",L2*Resumen!$B$10/Resumen!$B$18) -> 1.4782307 | T2: =IF(S2="","",S2-Resumen!$B$8) -> -0.52176926 | U2: =IF(S2="","",IF(S2>=Resumen!$B$8,"CUMPLE","NO CUMPLE")) -> NO CUMPLE
A3: No | B3: 21700 | C3: Li-Ion 21700 | D3: 3.63 | E3: 4900 | F3: 1 | G3: 1 | H3: =IF(OR(D3="",F3=""),"",D3*F3) -> 3.63 | I3: =IF(OR(E3="",G3=""),"",E3*G3) -> 4900 | J3: =IF(OR(H3="",I3=""),"",H3*I3/1000) -> 17.787 | K3: 0.9 | L3: =IF(J3="","",J3*K3) -> 16.0083 | O3: =IF(M3="","",M3*F3*G3+N3) | R3: =IF(P3="","",P3*F3*G3+Q3) | S3: =IF(OR(L3="",Resumen!$B$18=0),"",L3*Resumen!$B$10/Resumen!$B$18) -> 1.1843824 | T3: =IF(S3="","",S3-Resumen!$B$8) -> -0.81561756 | U3: =IF(S3="","",IF(S3>=Resumen!$B$8,"CUMPLE","NO CUMPLE")) -> NO CUMPLE
A4: No | F4: 1 | G4: 1 | H4: =IF(OR(D4="",F4=""),"",D4*F4) | I4: =IF(OR(E4="",G4=""),"",E4*G4) | J4: =IF(OR(H4="",I4=""),"",H4*I4/1000) | K4: 0.9 | L4: =IF(J4="","",J4*K4) | O4: =IF(M4="","",M4*F4*G4+N4) | R4: =IF(P4="","",P4*F4*G4+Q4) | S4: =IF(OR(L4="",Resumen!$B$18=0),"",L4*Resumen!$B$10/Resumen!$B$18) | T4: =IF(S4="","",S4-Resumen!$B$8) | U4: =IF(S4="","",IF(S4>=Resumen!$B$8,"CUMPLE","NO CUMPLE"))
A5: No | F5: 1 | G5: 1 | H5: =IF(OR(D5="",F5=""),"",D5*F5) | I5: =IF(OR(E5="",G5=""),"",E5*G5) | J5: =IF(OR(H5="",I5=""),"",H5*I5/1000) | K5: 0.9 | L5: =IF(J5="","",J5*K5) | O5: =IF(M5="","",M5*F5*G5+N5) | R5: =IF(P5="","",P5*F5*G5+Q5) | S5: =IF(OR(L5="",Resumen!$B$18=0),"",L5*Resumen!$B$10/Resumen!$B$18) | T5: =IF(S5="","",S5-Resumen!$B$8) | U5: =IF(S5="","",IF(S5>=Resumen!$B$8,"CUMPLE","NO CUMPLE"))
A6: No | F6: 1 | G6: 1 | H6: =IF(OR(D6="",F6=""),"",D6*F6) | I6: =IF(OR(E6="",G6=""),"",E6*G6) | J6: =IF(OR(H6="",I6=""),"",H6*I6/1000) | K6: 0.9 | L6: =IF(J6="","",J6*K6) | O6: =IF(M6="","",M6*F6*G6+N6) | R6: =IF(P6="","",P6*F6*G6+Q6) | S6: =IF(OR(L6="",Resumen!$B$18=0),"",L6*Resumen!$B$10/Resumen!$B$18) | T6: =IF(S6="","",S6-Resumen!$B$8) | U6: =IF(S6="","",IF(S6>=Resumen!$B$8,"CUMPLE","NO CUMPLE"))
A7: No | F7: 1 | G7: 1 | H7: =IF(OR(D7="",F7=""),"",D7*F7) | I7: =IF(OR(E7="",G7=""),"",E7*G7) | J7: =IF(OR(H7="",I7=""),"",H7*I7/1000) | K7: 0.9 | L7: =IF(J7="","",J7*K7) | O7: =IF(M7="","",M7*F7*G7+N7) | R7: =IF(P7="","",P7*F7*G7+Q7) | S7: =IF(OR(L7="",Resumen!$B$18=0),"",L7*Resumen!$B$10/Resumen!$B$18) | T7: =IF(S7="","",S7-Resumen!$B$8) | U7: =IF(S7="","",IF(S7>=Resumen!$B$8,"CUMPLE","NO CUMPLE"))
A8: No | F8: 1 | G8: 1 | H8: =IF(OR(D8="",F8=""),"",D8*F8) | I8: =IF(OR(E8="",G8=""),"",E8*G8) | J8: =IF(OR(H8="",I8=""),"",H8*I8/1000) | K8: 0.9 | L8: =IF(J8="","",J8*K8) | O8: =IF(M8="","",M8*F8*G8+N8) | R8: =IF(P8="","",P8*F8*G8+Q8) | S8: =IF(OR(L8="",Resumen!$B$18=0),"",L8*Resumen!$B$10/Resumen!$B$18) | T8: =IF(S8="","",S8-Resumen!$B$8) | U8: =IF(S8="","",IF(S8>=Resumen!$B$8,"CUMPLE","NO CUMPLE"))
A9: No | F9: 1 | G9: 1 | H9: =IF(OR(D9="",F9=""),"",D9*F9) | I9: =IF(OR(E9="",G9=""),"",E9*G9) | J9: =IF(OR(H9="",I9=""),"",H9*I9/1000) | K9: 0.9 | L9: =IF(J9="","",J9*K9) | O9: =IF(M9="","",M9*F9*G9+N9) | R9: =IF(P9="","",P9*F9*G9+Q9) | S9: =IF(OR(L9="",Resumen!$B$18=0),"",L9*Resumen!$B$10/Resumen!$B$18) | T9: =IF(S9="","",S9-Resumen!$B$8) | U9: =IF(S9="","",IF(S9>=Resumen!$B$8,"CUMPLE","NO CUMPLE"))
A10: No | F10: 1 | G10: 1 | H10: =IF(OR(D10="",F10=""),"",D10*F10) | I10: =IF(OR(E10="",G10=""),"",E10*G10) | J10: =IF(OR(H10="",I10=""),"",H10*I10/1000) | K10: 0.9 | L10: =IF(J10="","",J10*K10) | O10: =IF(M10="","",M10*F10*G10+N10) | R10: =IF(P10="","",P10*F10*G10+Q10) | S10: =IF(OR(L10="",Resumen!$B$18=0),"",L10*Resumen!$B$10/Resumen!$B$18) | T10: =IF(S10="","",S10-Resumen!$B$8) | U10: =IF(S10="","",IF(S10>=Resumen!$B$8,"CUMPLE","NO CUMPLE"))
A11: No | F11: 1 | G11: 1 | H11: =IF(OR(D11="",F11=""),"",D11*F11) | I11: =IF(OR(E11="",G11=""),"",E11*G11) | J11: =IF(OR(H11="",I11=""),"",H11*I11/1000) | K11: 0.9 | L11: =IF(J11="","",J11*K11) | O11: =IF(M11="","",M11*F11*G11+N11) | R11: =IF(P11="","",P11*F11*G11+Q11) | S11: =IF(OR(L11="",Resumen!$B$18=0),"",L11*Resumen!$B$10/Resumen!$B$18) | T11: =IF(S11="","",S11-Resumen!$B$8) | U11: =IF(S11="","",IF(S11>=Resumen!$B$8,"CUMPLE","NO CUMPLE"))

Sheet Requisitos_CONAE
A1: Requisito | B1: Tema | C1: Descripción | D1: Valor útil para la planilla | E1: Fuente
A2: S1 | B2: Masa | C2: La masa combinada del CanSat y el contenedor debe ser de 500 g ± 10 g. | D2: Objetivo 500 g; rango permitido 490–510 g | E2: Apéndice A – Requisitos de Misión
A3: S2 | B3: Dimensiones | C3: El diámetro del CanSat debe ser de 95 mm. | D3: Ø 95 mm | E3: Apéndice A – Requisitos de Misión
A4: S3 | B4: Dimensiones | C4: La longitud total, incluidos los sistemas de descenso, debe estar entre 200 y 250 mm. | D4: 200–250 mm | E4: Apéndice A – Requisitos de Misión
A5: C9 | B5: Presupuesto | C5: El costo del CanSat debe ser inferior a $1.000.000. Herramientas de análisis y soporte en tierra no incluidas. | D5: < $1.000.000 ARS para el CanSat | E5: Apéndice A – Requisitos de Misión
A6: E1 | B6: Batería | C6: No se permiten baterías de polímero de litio. | D6: LiPo no permitida | E6: Apéndice A – Requisitos de Misión
A7: E2 | B7: Batería | C7: Se permiten alcalinas, Ni-Cd, Ni-MH o litio con empaque metálico tipo 18650; también baterías de botón. | D7: Usar química permitida | E7: Apéndice A – Requisitos de Misión
A8: E7 | B8: Autonomía | C8: El CanSat debe funcionar durante un mínimo de dos horas cuando esté integrado en el cohete. | D8: Autonomía mínima: 2 h | E8: Apéndice A – Requisitos de Misión
A9: M4 | B9: Conexión batería | C9: No se deben utilizar contactos de resorte para realizar conexiones eléctricas a las baterías. | D9: Evitar portapilas con contacto de resorte | E9: Apéndice A – Requisitos de Misión
